monobank_client/__init__.py
monobank_client/client.py
monobank_client/settings.py
monobank_client/utils.py
monobank_client-0.1.2.dist-info/LICENSE
monobank_client-0.1.2.dist-info/METADATA
monobank_client-0.1.2.dist-info/WHEEL
monobank_client-0.1.2.dist-info/top_level.txt
monobank_client-0.1.2.dist-info/RECORD
