Metadata-Version: 2.1
Name: monobank-client
Version: 0.1.2
Summary: Monobank API client
Home-page: https://github.com/ortymid/python-monobank-client
Author: Dmytro Brykovets
Author-email: dmytro.brykovets@gmail.com
License: UNKNOWN
Platform: UNKNOWN
Classifier: Programming Language :: Python :: 3
Classifier: License :: OSI Approved :: MIT License
Classifier: Operating System :: OS Independent
Requires-Dist: requests
